saltext/mattermost/__init__.py
saltext/mattermost/version.py
saltext/mattermost/modules/__init__.py
saltext/mattermost/modules/mattermost.py
saltext/mattermost/returners/__init__.py
saltext/mattermost/returners/mattermost_returner.py
saltext/mattermost/runners/__init__.py
saltext/mattermost/runners/mattermost.py
saltext/mattermost/utils/__init__.py
saltext/mattermost/utils/mattermost.py
saltext.mattermost-1.0.0.dist-info/LICENSE
saltext.mattermost-1.0.0.dist-info/METADATA
saltext.mattermost-1.0.0.dist-info/NOTICE
saltext.mattermost-1.0.0.dist-info/WHEEL
saltext.mattermost-1.0.0.dist-info/entry_points.txt
saltext.mattermost-1.0.0.dist-info/top_level.txt
saltext.mattermost-1.0.0.dist-info/RECORD
